AUTHORS
LICENSE
MANIFEST.in
README
setup.py
configdir/__init__.py
configdir/django_confighelper.py
configdir/template.py
configdir/management/__init__.py
configdir/management/commands/__init__.py
configdir/management/commands/confignginx.py
django_configdir.egg-info/PKG-INFO
django_configdir.egg-info/SOURCES.txt
django_configdir.egg-info/dependency_links.txt
django_configdir.egg-info/entry_points.txt
django_configdir.egg-info/top_level.txt