Metadata-Version: 1.1
Name: django-configdir
Version: 0.1.10
Summary: A utility to create per-user, per-host configuration files for Django.
Home-page: http://github.com/woome/django_configdir
Author: Seb Potter
Author-email: seb@woome.com
License: GPLv2
Keywords: django configuration instance utility user
Platform: UNKNOWN
Classifier: Development Status :: 4 - Beta
Classifier: Topic :: Utilities
Classifier: License :: OSI Approved :: GNU General Public License (GPL)
Classifier: Framework :: Django
Requires: django
